fake_bpy/__init__.py
fake_bpy/context.py
fake_bpy/types.py
fake_bpy/utils.py
fake_bpy-0.1.0.dist-info/LICENSE
fake_bpy-0.1.0.dist-info/METADATA
fake_bpy-0.1.0.dist-info/WHEEL
fake_bpy-0.1.0.dist-info/top_level.txt
fake_bpy-0.1.0.dist-info/RECORD
