Metadata-Version: 2.1
Name: fake-bpy
Version: 0.1.0
Summary: Module with various useful utilities.
Home-page: https://github.com/ArjunSahlot/
Author: Arjun Sahlot
Author-email: iarjun.sahlot@gmail.com
License: UNKNOWN
Platform: UNKNOWN
Classifier: Programming Language :: Python :: 3
Classifier: License :: OSI Approved :: GNU General Public License v2 or later (GPLv2+)
Classifier: Operating System :: OS Independent
